mario/__init__.py
mario/__main__.py
mario/app.py
mario/asynch.py
mario/cli.py
mario/cli_tools.py
mario/config.py
mario/declarative.py
mario/doc.py
mario/exceptions.py
mario/interfaces.py
mario/interpret.py
mario/plug.py
mario/plugins/__init__.py
mario/plugins/basic.py
mario/plugins/read.py
mario/plugins/read.toml
mario/plugins/write.py
mario/plugins/write.toml
mario/sphinx_click.py
mario/sphinx_jsonschema.py
mario/sphinx_marshmallow.py
mario/testing/atools.py
mario/traversals.py
mario/utils.py
mario-0.0.154.dist-info/entry_points.txt
mario-0.0.154.dist-info/LICENSE
mario-0.0.154.dist-info/WHEEL
mario-0.0.154.dist-info/METADATA
mario-0.0.154.dist-info/RECORD
