Metadata-Version: 2.1
Name: mario
Version: 0.0.154
Summary: 
License: GPL-3.0
Author: akb
Author-email: uBX6aXPqDSRrt92kha28@cordaz.com
Requires-Python: >=3.7,<4.0
Classifier: License :: OSI Approved :: GNU General Public License v3 (GPLv3)
Classifier: Programming Language :: Python :: 3
Classifier: Programming Language :: Python :: 3.7
Provides-Extra: docs
Requires-Dist: appdirs (==1.4.3)
Requires-Dist: asks (==2.3.6)
Requires-Dist: async_exit_stack (==1.0.1)
Requires-Dist: async_generator (==1.10)
Requires-Dist: attrs (==19.3.0)
Requires-Dist: bump2version (==0.5.11)
Requires-Dist: click (==7.0)
Requires-Dist: docutils (==0.14)
Requires-Dist: importlib_metadata (==0.23)
Requires-Dist: marshmallow (==3.2.1)
Requires-Dist: marshmallow-jsonschema (>=0.8.0,<0.9.0); extra == "docs"
Requires-Dist: parso (==0.5.1)
Requires-Dist: pyrsistent (==0.14.11)
Requires-Dist: pytest (>=5.0.0,<6.0.0)
Requires-Dist: pyyaml (==5.1.1)
Requires-Dist: sphinx (==2.1.2); extra == "docs"
Requires-Dist: sphinx-autodoc-typehints (>=1.7,<2.0); extra == "docs"
Requires-Dist: sphinx-click (>=2.2,<3.0); extra == "docs"
Requires-Dist: sphinx-jsonschema (>=1.9,<2.0); extra == "docs"
Requires-Dist: sphinx-rtd-theme (>=0.4.3,<0.5.0); extra == "docs"
Requires-Dist: toml (==0.10.0)
Requires-Dist: toolz (>=0.10.0,<0.11.0)
Requires-Dist: trio (==0.11.0)
Requires-Dist: trio_typing (==0.2.0)
Requires-Dist: xmltodict (==0.12.0)
